{
  "action_count": 5,
  "blocked_check_count": 0,
  "check_count": 15,
  "checks": [
    {
      "detail": "Live trading feature flag is disabled.",
      "name": "live_trading_disabled",
      "passed": true,
      "severity": "PASS"
    },
    {
      "detail": "Live kill switch is enabled.",
      "name": "kill_switch_enabled",
      "passed": true,
      "severity": "PASS"
    },
    {
      "detail": "No private key is configured.",
      "name": "private_key_absent",
      "passed": true,
      "severity": "PASS"
    },
    {
      "detail": "Configure the isolated live wallet public address before funding.",
      "name": "isolated_wallet_address",
      "passed": false,
      "severity": "ACTION"
    },
    {
      "detail": "Live wallet must be separate from the main wallet.",
      "name": "wallet_isolation",
      "passed": false,
      "severity": "ACTION"
    },
    {
      "detail": "Planned chain is Base.",
      "name": "planned_chain_base",
      "passed": true,
      "severity": "PASS"
    },
    {
      "detail": "Live chain allowlist is restricted to Base.",
      "name": "chain_allowlist_base",
      "passed": true,
      "severity": "PASS"
    },
    {
      "detail": "Live token allowlist includes USDC and WETH.",
      "name": "token_allowlist_usdc_weth",
      "passed": true,
      "severity": "PASS"
    },
    {
      "detail": "Planned funding is within the $500 tiny-pilot ceiling.",
      "name": "planned_wallet_ceiling",
      "passed": true,
      "severity": "PASS"
    },
    {
      "detail": "Planned ETH gas budget is within preparation range.",
      "name": "planned_gas_budget",
      "passed": true,
      "severity": "PASS"
    },
    {
      "detail": "Set CRYPTOAI_MAX_LIVE_WALLET_USD to a value > 0 and <= 500 before any live pilot.",
      "name": "configured_wallet_ceiling",
      "passed": false,
      "severity": "ACTION"
    },
    {
      "detail": "Set CRYPTOAI_MAX_LIVE_TRADE_USD to a small value, usually $25-$50, before any live pilot.",
      "name": "configured_trade_cap",
      "passed": false,
      "severity": "ACTION"
    },
    {
      "detail": "Set CRYPTOAI_MAX_DAILY_LOSS_USD to a value > $0 and no larger than the live trade cap.",
      "name": "configured_daily_loss",
      "passed": false,
      "severity": "ACTION"
    },
    {
      "detail": "Manual confirmation is required.",
      "name": "manual_confirmation_required",
      "passed": true,
      "severity": "PASS"
    },
    {
      "detail": "Transaction simulation is required.",
      "name": "transaction_simulation_required",
      "passed": true,
      "severity": "PASS"
    }
  ],
  "generated_at": "2026-06-30T12:53:56Z",
  "live_kill_switch_enabled": true,
  "live_trading_approval": false,
  "live_trading_enabled": false,
  "live_wallet_configured": false,
  "max_prep_wallet_usd": "500.0000",
  "max_tiny_trade_usd": "100.0000",
  "mode": "paper",
  "notes": [
    "Wallet Preflight is preparation-only and never approves live trading.",
    "Do not configure private keys until the transaction path, simulation gate, and manual review are complete.",
    "The first real-money pilot should use an isolated wallet on Base with a total wallet ceiling of $500 or less."
  ],
  "overall_status": "WALLET_PREP_ACTION",
  "planned_chain": "base",
  "planned_eth_gas_usd": "50.0000",
  "planned_total_usd": "500.0000",
  "planned_usdc_usd": "450.0000",
  "private_key_configured": false,
  "wallet_preflight_allowed": false
}